{
    "manifest": {
        "id": "calendar-beta",
        "author": "宇桐非",
        "version": "2.0.0",
        "pluginVersion": "2.0.0"
    },
    "description": {
        "original": "Calendar view of your daily notes",
        "translation": "Calendar view of your daily notes"
    },
    "dict": {
        ".setName(\"Max incomplete tasks shown\")": ".setName(\"显示的最大未完成任务数\")",
        ".setName(\"Words per dot\")": ".setName(\"每个点代表的字数\")",
        ".setName(\"Display\")": ".setName(\"显示\")",
        ".setDesc(\"Limit the number of dots shown for incomplete tasks\")": ".setDesc(\"限制显示的未完成任务的点的数量\")",
        ".setDesc(\"How many words should be represented by a single dot?\")": ".setDesc(\"单个点应该代表多少字？\")",
        ".createEl(\"button\", { text: \"Never mind\" })": ".createEl(\"button\", { text: \"算了\" })",
        ".setTitle(\"Delete\")": ".setTitle(\"删除\")",
        ".textContent = \"W\"": ".textContent = \"周\"",
        ".textContent = \"General Settings\"": ".textContent = \"常规设置\"",
        ".textContent = \"Sources\"": ".textContent = \"来源\"",
        ".textContent = \"Configure what appears on the calendar and what shows in the hover menu.\\n    Drag to reorder.\"": ".textContent = \"配置日历上显示的内容以及悬停菜单中显示的内容。\\n    拖动以重新排序。\"",
        ".textContent = \"Localization\"": ".textContent = \"本地化\"",
        "name: \"Links\"": "name: \"链接\"",
        "name: \"Tasks\"": "name: \"任务\"",
        "name: \"Words\"": "name: \"字数\"",
        "name: \"Backlinks\"": "name: \"反向链接\"",
        "name: \"Emoji Tags\"": "name: \"表情标签\"",
        "name: \"offset\"": "name: \"偏移\"",
        "name: \"hide\"": "name: \"隐藏\"",
        "name: \"shouldConfirmBeforeCreate\"": "name: \"创建前应确认\"",
        "name: \"showWeeklyNote\"": "name: \"显示每周笔记\"",
        "name: \"weekStart\"": "name: \"周开始\"",
        "name: \"localeOverride\"": "name: \"地方设置覆盖\"",
        "name: \"Confirm before creating new note\"": "name: \"创建新笔记前确认\"",
        "name: \"Show week numbers\"": "name: \"显示周数\"",
        "name: \"Start week on\"": "name: \"周从何时开始\"",
        "name: \"Locale\"": "name: \"地方设置\"",
        "name: \"Open view\"": "name: \"打开视图\"",
        "name: \"Toggle week numbers\"": "name: \"切换周数\"",
        "name: \"Reveal active note\"": "name: \"显示活动笔记\"",
        "description: \"Show tags containing emojis directly on the calendar face\"": "description: \"直接在日历面上显示包含表情符号的标签\"",
        "description: \"Track your pending tasks for any given day\"": "description: \"跟踪任何给定日期的待办任务\"",
        "description: \"Visualize the word count of your daily note.\"": "description: \"可视化你的每日笔记的字数\"",
        "description: \"Show how many notes use a Zettelkasten prefix matching the current day\"": "description: \"显示有多少笔记使用了与当前日期匹配的Zettelkasten前缀\"",
        "description: \"Show a confirmation modal before creating a new note\"": "description: \"在创建新笔记前显示确认模态框\"",
        "description: \"Enable this to add a column with the week number\"": "description: \"启用此项以添加一个显示周数的列\"",
        "description: \"Choose what day of the week to start. Select 'locale default' to use the default specified by moment.js\"": "description: \"选择一周的开始日期。选择‘语言环境默认’以使用moment.js指定的默认值\"",
        "description: \"Override the locale used by the calendar and other plugins\"": "description: \"覆盖日历和其他插件所使用的地方设置\"",
        ".addOption(\"calendar-and-menu\", \"On Calendar\")": ".addOption(\"calendar-and-menu\", \"在日历上\")",
        ".addOption(\"menu\", \"In Menu\")": ".addOption(\"menu\", \"在菜单中\")",
        ".addOption(\"none\", \"Hidden\")": ".addOption(\"none\", \"隐藏\")"
    }
}