{
    "manifest": {
        "author": "",
        "version": "-1"
    },
    "dict": {
        "setPlaceholder('Search Style Settings...'": "setPlaceholder('搜索样式设置...'",
        "'Export'": "'输出'",
        "'Import'": "'输入'",
        ".setName('Import style setting'": ".setName('导入样式设置'",
        ".setDesc('Import an entire or partial configuration. Warning: this may override existing settings'": ".setDesc('导入整个或部分配置。警告：这可能会覆盖现有设置'",
        "text: 'Import from file'": "text: '从文件导入'",
        ".setButtonText('Save')": ".setButtonText('保存')",
        ".setName(`Export settings for: ${this.section}`": ".setName(`导出的设置: ${this.section}`",
        "text: 'Copy to clipboard'": "text: '复制到剪贴板'",
        "text: 'Download'": "text: '下载'",
        "name: 'Show style settings view'": "name: '显示样式设置视图'"
    }
}
